oslodb_sqlachemy_exceptions/__init__.py
oslodb_sqlachemy_exceptions/exceptions.py
oslodb_sqlachemy_exceptions/reflection.py
oslodb_sqlachemy_exceptions/sqla_errors.py
oslodb_sqlachemy_exceptions/warning.py
oslodb_sqlachemy_exceptions-0.2.0.dist-info/WHEEL
oslodb_sqlachemy_exceptions-0.2.0.dist-info/METADATA
oslodb_sqlachemy_exceptions-0.2.0.dist-info/RECORD
