Metadata-Version: 2.1
Name: oslodb-sqlachemy-exceptions
Version: 0.2.0
Summary: 
Author: Douglas Bett
Author-email: bettdalpha@gmail.com
Requires-Python: >=3.9,<4.0
Classifier: Programming Language :: Python :: 3
Classifier: Programming Language :: Python :: 3.9
Classifier: Programming Language :: Python :: 3.10
Requires-Dist: SQLAlchemy (>=1.2.0,<2.0.0)
Requires-Dist: debtcollector (>=1.2.0,<2.0.0)
